Metadata-Version: 2.1
Name: xdnlp
Version: 0.0.9
Summary: An efficient NLP tool.
Home-page: https://github.com/mikuh/xdnlp
Author: geb
Author-email: 853934146@qq.com
License: UNKNOWN
Platform: UNKNOWN
Classifier: Programming Language :: Python :: 3
Classifier: Operating System :: OS Independent
Requires-Python: >=3.6
License-File: LICENSE
Requires-Dist: numpy
Requires-Dist: pandas
Requires-Dist: nltk
